sqs_queue.py
sqs_queue-0.6.6.dist-info/LICENSE.txt
sqs_queue-0.6.6.dist-info/METADATA
sqs_queue-0.6.6.dist-info/WHEEL
sqs_queue-0.6.6.dist-info/top_level.txt
sqs_queue-0.6.6.dist-info/RECORD
