Metadata-Version: 2.1
Name: sqs_queue
Version: 0.6.6
Summary: AWS SQS queue consumer/publisher
Home-page: http://github.com/Media-Platforms/py-sqs-queue
Author: Nic Wolff
Author-email: nwolff@hearst.com
License: MIT
License-File: LICENSE.txt
Requires-Dist: boto3
